simple_form/__init__.py
simple_form/models.py
simple_form/tests.py
simple_form/templates/simple_form/field.html
simple_form/templatetags/__init__.py
simple_form/templatetags/simple_form.py
django_simple_form-0.0.2.dist-info/LICENSE
django_simple_form-0.0.2.dist-info/METADATA
django_simple_form-0.0.2.dist-info/WHEEL
django_simple_form-0.0.2.dist-info/top_level.txt
django_simple_form-0.0.2.dist-info/RECORD
