Metadata-Version: 2.1
Name: django-simple-form
Version: 0.0.2
Summary: Django-simple-form is a simple way to build your forms in HTML-level
Home-page: https://github.com/daniellbastos/django-simple-form/
Author: Daniel Bastos
Author-email: danielfloresbastos@gmail.com
Keywords: django,widget,form,field
Classifier: Framework :: Django
Classifier: Programming Language :: Python :: 3.5
Classifier: Programming Language :: Python :: 3.6
Classifier: Programming Language :: Python :: 3.7
Classifier: Topic :: Software Development :: Libraries
License-File: LICENSE
